sources_1/new/spsram.v
`timescale 1ns / 1ps
module spsram #(parameter DATA_WIDTH = 8,parameter ADDRESS_WIDTH = 8
)(
input wire  clk,wre,oe,ce,rst,
input wire [ADDRESS_WIDTH-1:0]addr,
inout wire [DATA_WIDTH-1:0]data, // bidirectional data bus
output reg status
    );
    localparam DEPTH = 2**ADDRESS_WIDTH;

    reg [DATA_WIDTH-1:0] mem[0:DEPTH-1];
    reg [DATA_WIDTH-1:0] TEMPDATA;

    always @(posedge clk or negedge rst)
        begin

            if(!rst)
                begin
                status <= 1'b0;
                TEMPDATA <= 0;
                end

            else

                begin
                status <= 0;
                if(wre && ce)
                    begin
                        mem[addr] <= data;
                        status <= 1'b1;
                    end
                else if(oe && !wre && ce)
                    begin
                        TEMPDATA <= mem[addr];
                        status <= 1'b1;
                    end
            end
    end
    assign data = (!wre && ce && oe&& status)? TEMPDATA:{DATA_WIDTH{1'hz}};

endmodule

sources_1/new/controller.v
`timescale 1ns / 1ps

module controller #(parameter DATA_WIDTH = 8, parameter ADDRESS_WIDTH = 8)(
input wire req,rw,clk,rst,bmode,abort,ram_stat,
input [3:0]burst_len,
inout wire [DATA_WIDTH-1:0]data_cn_ram,
input wire [ADDRESS_WIDTH-1:0]addr,
output wire [ADDRESS_WIDTH-1:0]sram_addr,
output reg wre,oe,ce,tri_o,
output reg done,error_flag,
output busy,
inout wire [DATA_WIDTH-1:0]data_cn_in_out
    );
    //internal registers
    reg [ADDRESS_WIDTH-1:0]addr_reg;
    reg [DATA_WIDTH-1:0] data_reg;
    reg [1:0]try;
    reg rw_reg,bmode_reg;
    reg [3:0]state,next_state;
    reg [3:0]burst_len_reg;
    reg [3:0]burst_count;
    //internal registers

    //local parameters
    localparam IDLE = 4'b0001;
    localparam PRE_IDLE = 4'b0000;
    localparam PRE = 4'b0010;
    localparam WRITE = 4'b0011;
    localparam READ = 4'b0100;
    localparam BE = 4'b0101;

    localparam MAXTRY = 2'b11;

    //local parameters

    //cont assignments
    assign data_cn_ram = tri_o == 0? data_reg : {DATA_WIDTH{1'hz}};
    assign busy = (state == IDLE || state == PRE_IDLE)? 1'b0:1'b1;
    assign sram_addr = addr_reg;
    //cont assignments

    //state-register
    always @(posedge clk or negedge rst)
        begin
            if(!rst)
                begin
                    state <= PRE_IDLE;
                    try <= 2'b00;
                    addr_reg  <= 0;
                    data_reg  <= 0;
                    rw_reg    <= 0;
                    error_flag <=0;
                    done <=0;
                    burst_count <= 1'b0;
                    bmode_reg <= 0;
                    burst_len_reg <= 0;

                end
             else
             begin
                state <= next_state;
                done <= 0;

                    if(state == IDLE && req)
                        begin
                            addr_reg <= addr;
                            rw_reg <= rw;
                            bmode_reg <= bmode;
                            burst_len_reg <= burst_len;
                            burst_count <= 1'b0;
                            error_flag <=0;
                            if(rw)
                                data_reg <= data_cn_in_out;
                        end
                    else if(state == WRITE || state == READ)
                            begin
                                if(ram_stat && bmode_reg)
                                    begin
                                            if(burst_count < burst_len_reg -1)
                                                begin
                                                    burst_count <= burst_count +1'b1;
                                                    addr_reg <= addr_reg + 1'b1;
                                                end
                                    end
                         end
                end
        end
    //state-register

    //next-state-logic
        always @(*)

        begin
        next_state = state;
            case(state)

                PRE_IDLE : next_state = IDLE;

                IDLE: begin
                            if(req)
                            next_state = PRE;
                            else
                            next_state = IDLE;
                        end

                PRE: begin
                            if(rw_reg)
                            next_state = WRITE;
                            else
                            next_state = READ;
                     end
                WRITE: begin
                            if(ram_stat && bmode_reg)
                                begin

                                            if(burst_count == burst_len_reg -1)
                                                next_state = BE;
                                            else
                                                next_state = WRITE;


                                end
                            else if(ram_stat && ~bmode_reg)
                                        next_state = IDLE;
                        end
                READ: begin
                            if(ram_stat && bmode_reg)
                                begin

                                            if(burst_count == burst_len_reg -1)
                                                next_state = BE;
                                            else
                                                next_state = READ;


                                end
                            else if(ram_stat && ~bmode_reg)
                                        next_state = IDLE;
                        end
                BE: next_state = IDLE;
            endcase
        end
    //next-state-logic

    //output logic
        always @(*)
                begin
                    case(state)
                        PRE_IDLE:
                            begin
                                ce = 1'b0;
                                oe = 1'b0;
                                wre = 1'b0;
                                tri_o = 1'b1;
                            end
                        IDLE:
                            begin
                                ce = 1'b0;
                                oe = 1'b0;
                                wre = 1'b0;
                                tri_o = 1'b1;
                            end
                        PRE:
                            begin
                                ce = 1'b0;
                                oe = 1'b0;
                                wre = 1'b0;
                                tri_o = 1'b1;
                            end
                        WRITE:
                            begin
                                ce = 1'b1;
                                oe = 1'b0;
                                wre = 1'b1;
                                tri_o = 1'b0;
                            end
                         READ:
                            begin
                                ce = 1'b1;
                                oe = 1'b1;
                                wre = 1'b0;
                                tri_o = 1'b1;
                            end
                          BE:
                            begin
                                ce = 1'b0;
                                oe = 1'b0;
                                wre = 1'b0;
                                tri_o = 1'b1;
                            end
                    endcase
                end
    //output logic
endmodule

sim_1/new/controller_tb.v
`timescale 1ns / 1ps
module controller_tb(

    );
        parameter DATA_WIDTH = 8;
        parameter ADDRESS_WIDTH = 8;
        reg req,rw,clk,rst,bmode,abort;
        reg [3:0]burst_len;
        wire [DATA_WIDTH-1:0]data_cn_ram;
        reg [ADDRESS_WIDTH-1:0]addr;
        wire wre,oe,ce,tri_o;
        wire ram_stat;
        wire busy;
        wire [ADDRESS_WIDTH-1:0]sram_addr;
        wire [DATA_WIDTH-1:0]data_cn_in_out;
        reg [DATA_WIDTH-1:0]test_data;

        controller uut(
            .clk(clk),
            .rst(rst),
            .req(req),
            .rw(rw),
            .bmode(bmode),
            .abort(abort),
            .ram_stat(ram_stat),
            .burst_len(burst_len),
            .data_cn_ram(data_cn_ram),
            .addr(addr),
            .wre(wre),
            .oe(oe),
            .ce(ce),
            .tri_o(tri_o),
            .busy(busy),
            .data_cn_in_out(data_cn_in_out),
            .sram_addr(sram_addr)

        );
        spsram uut1(
        .oe(oe),
        .wre(wre),
        .ce(ce),
        .addr(sram_addr),
        .data(data_cn_ram),
        .status(ram_stat),
        .clk(clk),
        .rst(rst)
        );

        assign data_cn_in_out = (rw) ? test_data : {DATA_WIDTH{1'bz}};
        always #5 clk = ~clk;

        initial begin
            $dumpfile("wave.vcd");
            $dumpvars(0,controller_tb);
            clk = 0;
            rst = 1'b0;
            addr = 0;
            req = 0;
            rw = 0;
            bmode = 0;
            test_data = 0;
            #10;
            rst = 1'b1;
            addr = 8'b0000_0000;
            rw = 1'b1;
            req = 1;
            test_data = 8'b0000_0011;
            #30;
            req = 0;
            #40;
            req = 1'b1;
            addr = 8'b0000_0000;
            rw = 1'b0;
            #40;
            req = 0;
            #40;

        $finish;
        end
endmodule

wave.vcd
$date
	Fri Sep 11 11:21:09 2026
$end
$version
	Icarus Verilog
$end
$timescale
	1ps
$end
$scope module controller_tb $end
$var wire 8 ! data_cn_ram [7:0] $end
$var wire 1 " wre $end
$var wire 1 # tri_o $end
$var wire 8 $ sram_addr [7:0] $end
$var wire 1 % ram_stat $end
$var wire 1 & oe $end
$var wire 8 ' data_cn_in_out [7:0] $end
$var wire 1 ( ce $end
$var wire 1 ) busy $end
$var parameter 32 * ADDRESS_WIDTH $end
$var parameter 32 + DATA_WIDTH $end
$var reg 1 , abort $end
$var reg 8 - addr [7:0] $end
$var reg 1 . bmode $end
$var reg 4 / burst_len [3:0] $end
$var reg 1 0 clk $end
$var reg 1 1 req $end
$var reg 1 2 rst $end
$var reg 1 3 rw $end
$var reg 8 4 test_data [7:0] $end
$scope module uut $end
$var wire 1 , abort $end
$var wire 8 5 addr [7:0] $end
$var wire 1 . bmode $end
$var wire 4 6 burst_len [3:0] $end
$var wire 1 0 clk $end
$var wire 8 7 data_cn_in_out [7:0] $end
$var wire 8 8 data_cn_ram [7:0] $end
$var wire 1 1 req $end
$var wire 1 2 rst $end
$var wire 1 3 rw $end
$var wire 8 9 sram_addr [7:0] $end
$var wire 1 % ram_stat $end
$var wire 1 ) busy $end
$var parameter 32 : ADDRESS_WIDTH $end
$var parameter 4 ; BE $end
$var parameter 32 < DATA_WIDTH $end
$var parameter 4 = IDLE $end
$var parameter 2 > MAXTRY $end
$var parameter 4 ? PRE $end
$var parameter 4 @ PRE_IDLE $end
$var parameter 4 A READ $end
$var parameter 4 B WRITE $end
$var reg 8 C addr_reg [7:0] $end
$var reg 1 D bmode_reg $end
$var reg 4 E burst_count [3:0] $end
$var reg 4 F burst_len_reg [3:0] $end
$var reg 1 ( ce $end
$var reg 8 G data_reg [7:0] $end
$var reg 1 H done $end
$var reg 1 I error_flag $end
$var reg 4 J next_state [3:0] $end
$var reg 1 & oe $end
$var reg 1 K rw_reg $end
$var reg 4 L state [3:0] $end
$var reg 1 # tri_o $end
$var reg 2 M try [1:0] $end
$var reg 1 " wre $end
$upscope $end
$scope module uut1 $end
$var wire 8 N addr [7:0] $end
$var wire 1 ( ce $end
$var wire 1 0 clk $end
$var wire 8 O data [7:0] $end
$var wire 1 & oe $end
$var wire 1 2 rst $end
$var wire 1 " wre $end
$var parameter 32 P ADDRESS_WIDTH $end
$var parameter 32 Q DATA_WIDTH $end
$var parameter 32 R DEPTH $end
$var reg 8 S TEMPDATA [7:0] $end
$var reg 1 % status $end
$upscope $end
$upscope $end
$enddefinitions $end
$comment Show the parameter values. $end
$dumpall
b100000000 R
b1000 Q
b1000 P
b11 B
b100 A
b0 @
b10 ?
b11 >
b1 =
b1000 <
b101 ;
b1000 :
b1000 +
b1000 *
$end
#0
$dumpvars
b0 S
bz O
b0 N
b0 M
b0 L
0K
b1 J
0I
0H
b0 G
b0 F
b0 E
0D
b0 C
b0 9
bz 8
bz 7
bx 6
b0 5
b0 4
03
02
01
00
bx /
0.
b0 -
x,
0)
0(
bz '
0&
0%
b0 $
1#
0"
bz !
$end
#5000
10
#10000
b1 J
b11 '
b11 7
00
b11 4
11
13
12
#15000
b10 J
b1 L
10
#20000
00
#25000
1)
b11 J
b11 G
bx F
1K
b10 L
10
#30000
00
#35000
b11 !
b11 8
b11 O
0#
1"
1(
b11 L
10
#40000
00
01
#45000
b1 J
1%
10
#50000
00
#55000
bz !
bz 8
bz O
0)
1#
0"
0(
b1 L
1%
10
#60000
00
#65000
0%
10
#70000
00
#75000
10
#80000
bz '
bz 7
b10 J
00
03
11
#85000
1)
b100 J
0K
b10 L
10
#90000
00
#95000
1&
1(
b100 L
10
#100000
00
#105000
b11 !
b11 8
b11 O
b1 J
1%
b11 S
10
#110000
00
#115000
bz !
bz 8
bz O
0)
0&
0(
b10 J
b1 L
1%
10
#120000
b1 J
00
01
#125000
0%
10
