sources_1/new/spsram.v
`timescale 1ns / 1ps
module spsram #(parameter DATA_WIDTH = 8,parameter ADDRESS_WIDTH = 8
)(
input wire  clk,wre,oe,ce,rst,
input wire [ADDRESS_WIDTH-1:0]addr,
inout wire [DATA_WIDTH-1:0]data, // bidirectional data bus
output reg status
    );
    localparam DEPTH = 2**ADDRESS_WIDTH;

    reg [DATA_WIDTH-1:0] mem[0:DEPTH-1];
    reg [DATA_WIDTH-1:0] TEMPDATA;

    always @(posedge clk or negedge rst)
        begin

            if(!rst)
                begin
                status <= 1'b0;
                TEMPDATA <= 0;
                end

            else

                begin
                status <= 0;
                if(wre && ce)
                    begin
                        mem[addr] <= data;
                        status <= 1'b1;
                    end
                else if(oe && !wre && ce)
                    begin
                        TEMPDATA <= mem[addr];
                        status <= 1'b1;
                    end
            end
    end
    assign data = (!wre && ce && oe&& status)? TEMPDATA:{DATA_WIDTH{1'hz}};

endmodule

sources_1/new/controller.v
`timescale 1ns / 1ps

module controller #(parameter DATA_WIDTH = 8, parameter ADDRESS_WIDTH = 8)(
input wire req,rw,clk,rst,bmode,abort,ram_stat,data_valid,
input [3:0]burst_len,
inout wire [DATA_WIDTH-1:0]data_cn_ram,
input wire [ADDRESS_WIDTH-1:0]addr,
output wire [ADDRESS_WIDTH-1:0]sram_addr,
output reg wre,oe,ce,tri_o,
output reg done,error_flag,
output busy,
inout wire [DATA_WIDTH-1:0]data_cn_in_out
    );
    //internal registers
    reg [ADDRESS_WIDTH-1:0]addr_reg;
    reg [DATA_WIDTH-1:0] data_reg;
    reg [1:0]try;
    reg rw_reg,bmode_reg;
    reg [3:0]state,next_state;
    reg [3:0]burst_len_reg;
    reg [3:0]burst_count;
    //internal registers

    //local parameters
    localparam IDLE = 4'b0001;
    localparam PRE_IDLE = 4'b0000;
    localparam PRE = 4'b0010;
    localparam WRITE = 4'b0011;
    localparam READ = 4'b0100;
    localparam BE = 4'b0101;

    localparam MAXTRY = 2'b11;

    //local parameters

    //cont assignments
    assign data_cn_ram = tri_o == 0? data_reg : {DATA_WIDTH{1'hz}};
    assign busy = (state == IDLE || state == PRE_IDLE)? 1'b0:1'b1;
    assign sram_addr = addr_reg;
    assign data_cn_in_out = (state == READ && tri_o == 1)? data_cn_ram : {DATA_WIDTH{1'hz}};
    //cont assignments

    //state-register
    always @(posedge clk or negedge rst)
        begin
            if(!rst)
                begin
                    state <= PRE_IDLE;
                    try <= 2'b00;
                    addr_reg  <= 0;
                    data_reg  <= 0;
                    rw_reg    <= 0;
                    error_flag <=0;
                    done <=0;
                    burst_count <= 1'b0;
                    bmode_reg <= 0;
                    burst_len_reg <= 0;

                end
             else
             begin
                state <= next_state;
                done <= 0;

                    if(state == IDLE && req)
                        begin
                            addr_reg <= addr;
                            rw_reg <= rw;

                            bmode_reg <= bmode;
                            burst_len_reg <= burst_len;
                            burst_count <= 1'b0;
                            error_flag <=0;
                            if(rw)
                                data_reg <= data_cn_in_out;
                        end
                    if(burst_count == burst_len_reg - 1 && ram_stat)
                        done <= 1'b1;
                    else if(state == BE)
                    begin
                            if(rw_reg && bmode_reg && ram_stat && burst_count < burst_len_reg -1)
                            begin

                                burst_count <= burst_count +1'b1;
                                addr_reg <= addr_reg + 1'b1;
                            end
                            else if((~rw_reg && bmode_reg && ram_stat) && burst_count <burst_len_reg - 1)
                            begin
                                burst_count <= burst_count +1'b1;
                                addr_reg <= addr_reg + 1'b1;
                            end
                    end


                    else if(state == WRITE)
                            begin
                                if(bmode_reg)
                                    begin
                                        if(ram_stat)
                                        begin
                                                if(burst_count < burst_len_reg -1)
                                                    begin
                                                        data_reg <= data_cn_in_out;
                                                    end
                                        end
                                    end

                         end
                   /* else if(state == READ)
                        begin
                                if(!bmode_reg && ram_stat)
                                 done <= 1'b1;
                        end */


                end
        end
    //state-register

    //next-state-logic
        always @(*)

        begin
        next_state = state;
        if(abort)
            next_state = IDLE;
        else
            begin
            case(state)

                PRE_IDLE : next_state = IDLE;

                IDLE: begin
                            if(req)
                            next_state = PRE;
                            else
                            next_state = IDLE;
                        end

                PRE: begin
                            if(rw_reg)
                            next_state = WRITE;
                            else
                            next_state = READ;
                     end
                WRITE: begin
                            if(ram_stat && bmode_reg)
                                begin

                                            if(burst_count < burst_len_reg -1)
                                                next_state = BE;
                                            else
                                                next_state = IDLE;

                                end
                            else if(ram_stat && ~bmode_reg)
                                        next_state = IDLE;
                        end
                READ: begin
                            if(ram_stat && bmode_reg)
                                begin
                                            if(burst_count < burst_len_reg -1)
                                                next_state = BE;
                                            else
                                                next_state = IDLE;


                                end
                            else if(ram_stat && ~bmode_reg)
                                        next_state = IDLE;
                        end
                BE:
                    begin
                        if(bmode_reg && rw_reg)
                            next_state = WRITE;
                        else if(bmode_reg && ~rw_reg)
                            next_state = READ;
                        else
                            next_state = IDLE;
                    end
            endcase
            end
        end
    //next-state-logic

    //output logic
        always @(*)
                begin
                    case(state)
                        PRE_IDLE:
                            begin
                                ce = 1'b0;
                                oe = 1'b0;
                                wre = 1'b0;
                                tri_o = 1'b1;
                            end
                        IDLE:
                            begin
                                ce = 1'b0;
                                oe = 1'b0;
                                wre = 1'b0;
                                tri_o = 1'b1;
                            end
                        PRE:
                            begin
                                ce = 1'b0;
                                oe = 1'b0;
                                wre = 1'b0;
                                tri_o = 1'b1;
                            end
                        WRITE:
                            begin
                                ce = 1'b1;
                                oe = 1'b0;
                                wre = 1'b1;
                                tri_o = 1'b0;
                            end
                         READ:
                            begin
                                ce = 1'b1;
                                oe = 1'b1;
                                wre = 1'b0;
                                tri_o = 1'b1;
                            end
                          BE:
                            begin
                                ce = 1'b0;
                                oe = 1'b0;
                                wre = 1'b0;
                                tri_o = 1'b1;
                            end
                    endcase
                end
    //output logic
endmodule

sim_1/new/controller_tb.v
`timescale 1ns / 1ps

module controller_tb(

    );

parameter DATA_WIDTH = 8;
parameter ADDRESS_WIDTH = 8;

reg req,rw,clk,rst,bmode,abort;
reg [3:0] burst_len;

wire [DATA_WIDTH-1:0] data_cn_ram;
reg [ADDRESS_WIDTH-1:0] addr;

wire wre,oe,ce,tri_o;
wire ram_stat;
wire busy;
wire [ADDRESS_WIDTH-1:0] sram_addr;
wire [DATA_WIDTH-1:0] data_cn_in_out;

reg [DATA_WIDTH-1:0] test_data;
reg data_valid;


controller uut(
    .clk(clk),
    .rst(rst),
    .req(req),
    .rw(rw),
    .bmode(bmode),
    .abort(abort),
    .ram_stat(ram_stat),
    .burst_len(burst_len),
    .data_cn_ram(data_cn_ram),
    .addr(addr),
    .wre(wre),
    .oe(oe),
    .ce(ce),
    .tri_o(tri_o),
    .busy(busy),
    .data_cn_in_out(data_cn_in_out),
    .sram_addr(sram_addr),
    .data_valid(data_valid)
);


spsram uut1(
    .oe(oe),
    .wre(wre),
    .ce(ce),
    .addr(sram_addr),
    .data(data_cn_ram),
    .status(ram_stat),
    .clk(clk),
    .rst(rst)
);


assign data_cn_in_out =
       (rw) ? test_data : {DATA_WIDTH{1'bz}};


always #5 clk = ~clk;


initial begin

    $dumpfile("wave.vcd");
    $dumpvars(0,controller_tb);

    clk = 0;
    rst = 1'b0;
    addr = 0;
    req = 0;
    rw = 0;
    bmode = 0;
    test_data = 0;
    abort = 0;
    burst_len = 4'b0000;
    data_valid = 0;


    // Reset
    #10;
    rst = 1'b1;


    // Burst write: 01=02, 02=03, 03=07
    #20;
    addr = 8'h01;
    req = 1'b1;
    bmode = 1'b1;
    rw = 1'b1;
    burst_len = 4'd3;
    test_data = 8'h02;
    data_valid = 1'b1;

    #30;
    req = 1'b0;
    test_data = 8'h03;
    data_valid = 1'b1;

    #30;
    test_data = 8'h07;
    data_valid = 1'b1;

    #30;
    data_valid = 1'b0;
    bmode = 1'b0;
    rw = 1'b0;


    // Burst read: 01, 02, 03
    #30;
    req = 1'b1;
    bmode = 1'b1;
    rw = 1'b0;
    addr = 8'h01;
    burst_len = 4'd3;

    #90;
    req = 1'b0;
    bmode = 1'b0;


    // Normal write: 04=05
    #30;
    req = 1'b1;
    rw = 1'b1;
    test_data = 8'h05;
    bmode = 1'b0;
    addr = 8'h04;
    burst_len = 4'd1;

    #30;
    req = 1'b0;
    rw = 1'b0;


    // Normal read: 04
    #30;
    req = 1'b1;
    rw = 1'b0;
    bmode = 1'b0;
    addr = 8'h04;

    #30;
    req = 1'b0;


    // Normal writes: multiple addresses
    #30;
    req = 1'b1;
    rw = 1'b1;
    bmode = 1'b0;
    addr = 8'h10;
    test_data = 8'hAA;

    #30;
    req = 1'b0;

    #30;
    req = 1'b1;
    addr = 8'h11;
    test_data = 8'h55;

    #30;
    req = 1'b0;

    #30;
    req = 1'b1;
    addr = 8'h12;
    test_data = 8'hF0;

    #30;
    req = 1'b0;


    // Normal reads: verify multiple addresses
    #30;
    req = 1'b1;
    rw = 1'b0;
    addr = 8'h10;

    #30;
    req = 1'b0;

    #30;
    req = 1'b1;
    addr = 8'h11;

    #30;
    req = 1'b0;

    #30;
    req = 1'b1;
    addr = 8'h12;

    #30;
    req = 1'b0;


    // Single-word burst write
    #30;
    req = 1'b1;
    rw = 1'b1;
    bmode = 1'b1;
    burst_len = 4'd1;
    addr = 8'h20;
    test_data = 8'hCC;
    data_valid = 1'b1;

    #30;
    req = 1'b0;
    data_valid = 1'b0;
    bmode = 1'b0;
    rw = 1'b0;


    // Single-word burst read
    #30;
    req = 1'b1;
    rw = 1'b0;
    bmode = 1'b1;
    burst_len = 4'd1;
    addr = 8'h20;

    #30;
    req = 1'b0;
    bmode = 1'b0;


    // Burst write before abort
    #30;
    req = 1'b1;
    rw = 1'b1;
    bmode = 1'b1;
    burst_len = 4'd4;
    addr = 8'h30;
    test_data = 8'h11;
    data_valid = 1'b1;

    #30;
    req = 1'b0;
    test_data = 8'h22;
    data_valid = 1'b1;

    #20;
    abort = 1'b1;

    #10;
    abort = 1'b0;
    data_valid = 1'b0;
    bmode = 1'b0;
    rw = 1'b0;


    // Transaction after abort
    #30;
    req = 1'b1;
    rw = 1'b1;
    bmode = 1'b0;
    burst_len = 4'd1;
    addr = 8'h40;
    test_data = 8'h77;

    #30;
    req = 1'b0;
    rw = 1'b0;


    // Read after abort
    #30;
    req = 1'b1;
    rw = 1'b0;
    bmode = 1'b0;
    addr = 8'h40;

    #30;
    req = 1'b0;


    #50;

    $finish;

end

endmodule

wave.vcd
$date
	Tue Sep 15 14:19:18 2026
$end
$version
	Icarus Verilog
$end
$timescale
	1ps
$end
$scope module controller_tb $end
$var wire 8 ! data_cn_in_out [7:0] $end
$var wire 8 " data_cn_ram [7:0] $end
$var wire 1 # wre $end
$var wire 1 $ tri_o $end
$var wire 8 % sram_addr [7:0] $end
$var wire 1 & ram_stat $end
$var wire 1 ' oe $end
$var wire 1 ( ce $end
$var wire 1 ) busy $end
$var parameter 32 * ADDRESS_WIDTH $end
$var parameter 32 + DATA_WIDTH $end
$var reg 1 , abort $end
$var reg 8 - addr [7:0] $end
$var reg 1 . bmode $end
$var reg 4 / burst_len [3:0] $end
$var reg 1 0 clk $end
$var reg 1 1 data_valid $end
$var reg 1 2 req $end
$var reg 1 3 rst $end
$var reg 1 4 rw $end
$var reg 8 5 test_data [7:0] $end
$scope module uut $end
$var wire 1 , abort $end
$var wire 8 6 addr [7:0] $end
$var wire 1 . bmode $end
$var wire 4 7 burst_len [3:0] $end
$var wire 1 0 clk $end
$var wire 8 8 data_cn_in_out [7:0] $end
$var wire 8 9 data_cn_ram [7:0] $end
$var wire 1 1 data_valid $end
$var wire 1 2 req $end
$var wire 1 3 rst $end
$var wire 1 4 rw $end
$var wire 8 : sram_addr [7:0] $end
$var wire 1 & ram_stat $end
$var wire 1 ) busy $end
$var parameter 32 ; ADDRESS_WIDTH $end
$var parameter 4 < BE $end
$var parameter 32 = DATA_WIDTH $end
$var parameter 4 > IDLE $end
$var parameter 2 ? MAXTRY $end
$var parameter 4 @ PRE $end
$var parameter 4 A PRE_IDLE $end
$var parameter 4 B READ $end
$var parameter 4 C WRITE $end
$var reg 8 D addr_reg [7:0] $end
$var reg 1 E bmode_reg $end
$var reg 4 F burst_count [3:0] $end
$var reg 4 G burst_len_reg [3:0] $end
$var reg 1 ( ce $end
$var reg 8 H data_reg [7:0] $end
$var reg 1 I done $end
$var reg 1 J error_flag $end
$var reg 4 K next_state [3:0] $end
$var reg 1 ' oe $end
$var reg 1 L rw_reg $end
$var reg 4 M state [3:0] $end
$var reg 1 $ tri_o $end
$var reg 2 N try [1:0] $end
$var reg 1 # wre $end
$upscope $end
$scope module uut1 $end
$var wire 8 O addr [7:0] $end
$var wire 1 ( ce $end
$var wire 1 0 clk $end
$var wire 8 P data [7:0] $end
$var wire 1 ' oe $end
$var wire 1 3 rst $end
$var wire 1 # wre $end
$var parameter 32 Q ADDRESS_WIDTH $end
$var parameter 32 R DATA_WIDTH $end
$var parameter 32 S DEPTH $end
$var reg 8 T TEMPDATA [7:0] $end
$var reg 1 & status $end
$upscope $end
$upscope $end
$enddefinitions $end
$comment Show the parameter values. $end
$dumpall
b100000000 S
b1000 R
b1000 Q
b11 C
b100 B
b0 A
b10 @
b11 ?
b1 >
b1000 =
b101 <
b1000 ;
b1000 +
b1000 *
$end
#0
$dumpvars
b0 T
bz P
b0 O
b0 N
b0 M
0L
b1 K
0J
0I
b0 H
b0 G
b0 F
0E
b0 D
b0 :
bz 9
bz 8
b0 7
b0 6
b0 5
04
03
02
01
00
b0 /
0.
b0 -
0,
0)
0(
0'
0&
b0 %
1$
0#
bz "
bz !
$end
#5000
10
#10000
00
13
#15000
b1 M
10
#20000
00
#25000
10
#30000
b10 !
b10 8
b10 K
00
11
b10 5
b11 /
b11 7
14
1.
12
b1 -
b1 6
#35000
1)
b11 K
b10 H
b11 G
1E
1L
b1 %
b1 :
b1 O
b1 D
b10 M
10
#40000
00
#45000
b10 "
b10 9
b10 P
0$
1#
1(
b11 M
10
#50000
00
#55000
b101 K
1&
10
#60000
b11 !
b11 8
b101 K
00
b11 5
02
#65000
bz "
bz 9
bz P
1$
0#
0(
b11 K
1&
b11 H
b101 M
10
#70000
00
#75000
b11 "
b11 9
b11 P
0$
1#
1(
b10 %
b10 :
b10 O
b10 D
b1 F
b11 M
0&
10
#80000
00
#85000
b101 K
1&
10
#90000
b111 !
b111 8
00
b111 5
#95000
bz "
bz 9
bz P
1$
0#
0(
b11 K
b111 H
b101 M
1&
10
#100000
00
#105000
b111 "
b111 9
b111 P
0$
1#
1(
0&
b11 %
b11 :
b11 O
b11 D
b10 F
b11 M
10
#110000
00
#115000
b1 K
1&
10
#120000
bz !
bz 8
00
04
0.
01
#125000
bz "
bz 9
bz P
0)
1$
0#
0(
1&
1I
b1 M
10
#130000
00
#135000
1I
0&
10
#140000
00
#145000
0I
10
#150000
b10 K
00
1.
12
#155000
1)
b100 K
b0 F
0L
b1 %
b1 :
b1 O
b1 D
b10 M
10
#160000
00
#165000
1'
1(
b100 M
10
#170000
00
#175000
b10 !
b10 8
b10 "
b10 9
b10 P
b101 K
1&
b10 T
10
#180000
00
#185000
bz "
bz 9
bz P
bz !
bz 8
0'
0(
b100 K
1&
b101 M
10
#190000
00
#195000
1'
1(
b10 %
b10 :
b10 O
b10 D
b1 F
b100 M
0&
10
#200000
00
#205000
b11 !
b11 8
b11 "
b11 9
b11 P
b101 K
1&
b11 T
10
#210000
00
#215000
bz "
bz 9
bz P
bz !
bz 8
0'
0(
b100 K
b101 M
1&
10
#220000
00
#225000
1'
1(
0&
b11 %
b11 :
b11 O
b11 D
b10 F
b100 M
10
#230000
00
#235000
b111 !
b111 8
b111 "
b111 9
b111 P
b1 K
1&
b111 T
10
#240000
b1 K
00
0.
02
#245000
bz "
bz 9
bz P
0)
bz !
bz 8
0'
0(
1&
1I
b1 M
10
#250000
00
#255000
1I
0&
10
#260000
00
#265000
0I
10
#270000
b101 !
b101 8
b10 K
00
b1 /
b1 7
b100 -
b100 6
b101 5
14
12
#275000
1)
b11 K
b101 H
b0 F
b1 G
0E
1L
b100 %
b100 :
b100 O
b100 D
b10 M
10
#280000
00
#285000
b101 "
b101 9
b101 P
0$
1#
1(
b11 M
10
#290000
00
#295000
b1 K
1&
10
#300000
bz !
bz 8
b1 K
00
04
02
#305000
bz "
bz 9
bz P
0)
1$
0#
0(
1&
1I
b1 M
10
#310000
00
#315000
1I
0&
10
#320000
00
#325000
0I
10
#330000
b10 K
00
12
#335000
1)
b100 K
0L
b10 M
10
#340000
00
#345000
1'
1(
b100 M
10
#350000
00
#355000
b101 !
b101 8
b101 "
b101 9
b101 P
b1 K
1&
b101 T
10
#360000
b1 K
00
02
#365000
bz "
bz 9
bz P
0)
bz !
bz 8
0'
0(
1&
1I
b1 M
10
#370000
00
#375000
1I
0&
10
#380000
00
#385000
0I
10
#390000
b10101010 !
b10101010 8
b10 K
00
b10101010 5
b10000 -
b10000 6
14
12
#395000
1)
b11 K
b10101010 H
1L
b10000 %
b10000 :
b10000 O
b10000 D
b10 M
10
#400000
00
#405000
b10101010 "
b10101010 9
b10101010 P
0$
1#
1(
b11 M
10
#410000
00
#415000
b1 K
1&
10
#420000
b1 K
00
02
#425000
bz "
bz 9
bz P
0)
1$
0#
0(
1&
1I
b1 M
10
#430000
00
#435000
1I
0&
10
#440000
00
#445000
0I
10
#450000
b1010101 !
b1010101 8
b10 K
00
b1010101 5
b10001 -
b10001 6
12
#455000
1)
b11 K
b1010101 H
b10001 %
b10001 :
b10001 O
b10001 D
b10 M
10
#460000
00
#465000
b1010101 "
b1010101 9
b1010101 P
0$
1#
1(
b11 M
10
#470000
00
#475000
b1 K
1&
10
#480000
b1 K
00
02
#485000
bz "
bz 9
bz P
0)
1$
0#
0(
1&
1I
b1 M
10
#490000
00
#495000
1I
0&
10
#500000
00
#505000
0I
10
#510000
b11110000 !
b11110000 8
b10 K
00
b11110000 5
b10010 -
b10010 6
12
#515000
1)
b11 K
b11110000 H
b10010 %
b10010 :
b10010 O
b10010 D
b10 M
10
#520000
00
#525000
b11110000 "
b11110000 9
b11110000 P
0$
1#
1(
b11 M
10
#530000
00
#535000
b1 K
1&
10
#540000
b1 K
00
02
#545000
bz "
bz 9
bz P
0)
1$
0#
0(
1&
1I
b1 M
10
#550000
00
#555000
1I
0&
10
#560000
00
#565000
0I
10
#570000
bz !
bz 8
b10 K
00
b10000 -
b10000 6
04
12
#575000
1)
b100 K
0L
b10000 %
b10000 :
b10000 O
b10000 D
b10 M
10
#580000
00
#585000
1'
1(
b100 M
10
#590000
00
#595000
b10101010 !
b10101010 8
b10101010 "
b10101010 9
b10101010 P
b1 K
1&
b10101010 T
10
#600000
b1 K
00
02
#605000
bz "
bz 9
bz P
0)
bz !
bz 8
0'
0(
1&
1I
b1 M
10
#610000
00
#615000
1I
0&
10
#620000
00
#625000
0I
10
#630000
b10 K
00
b10001 -
b10001 6
12
#635000
1)
b100 K
b10001 %
b10001 :
b10001 O
b10001 D
b10 M
10
#640000
00
#645000
1'
1(
b100 M
10
#650000
00
#655000
b1010101 !
b1010101 8
b1010101 "
b1010101 9
b1010101 P
b1 K
1&
b1010101 T
10
#660000
b1 K
00
02
#665000
bz "
bz 9
bz P
0)
bz !
bz 8
0'
0(
1&
1I
b1 M
10
#670000
00
#675000
1I
0&
10
#680000
00
#685000
0I
10
#690000
b10 K
00
b10010 -
b10010 6
12
#695000
1)
b100 K
b10010 %
b10010 :
b10010 O
b10010 D
b10 M
10
#700000
00
#705000
1'
1(
b100 M
10
#710000
00
#715000
b11110000 !
b11110000 8
b11110000 "
b11110000 9
b11110000 P
b1 K
1&
b11110000 T
10
#720000
b1 K
00
02
#725000
bz "
bz 9
bz P
0)
bz !
bz 8
0'
0(
1&
1I
b1 M
10
#730000
00
#735000
1I
0&
10
#740000
00
#745000
0I
10
#750000
b11001100 !
b11001100 8
b10 K
00
11
b11001100 5
b100000 -
b100000 6
1.
14
12
#755000
1)
b11 K
b11001100 H
1E
1L
b100000 %
b100000 :
b100000 O
b100000 D
b10 M
10
#760000
00
#765000
b11001100 "
b11001100 9
b11001100 P
0$
1#
1(
b11 M
10
#770000
00
#775000
b1 K
1&
10
#780000
bz !
bz 8
b1 K
00
04
0.
01
02
#785000
bz "
bz 9
bz P
0)
1$
0#
0(
1&
1I
b1 M
10
#790000
00
#795000
1I
0&
10
#800000
00
#805000
0I
10
#810000
b10 K
00
1.
12
#815000
1)
b100 K
0L
b10 M
10
#820000
00
#825000
1'
1(
b100 M
10
#830000
00
#835000
b11001100 !
b11001100 8
b11001100 "
b11001100 9
b11001100 P
b1 K
1&
b11001100 T
10
#840000
b1 K
00
0.
02
#845000
bz "
bz 9
bz P
0)
bz !
bz 8
0'
0(
1&
1I
b1 M
10
#850000
00
#855000
1I
0&
10
#860000
00
#865000
0I
10
#870000
b10001 !
b10001 8
b10 K
00
11
b10001 5
b110000 -
b110000 6
b100 /
b100 7
1.
14
12
#875000
1)
b11 K
b10001 H
b100 G
1L
b110000 %
b110000 :
b110000 O
b110000 D
b10 M
10
#880000
00
#885000
b10001 "
b10001 9
b10001 P
0$
1#
1(
b11 M
10
#890000
00
#895000
b101 K
1&
10
#900000
b100010 !
b100010 8
b101 K
00
b100010 5
02
#905000
bz "
bz 9
bz P
1$
0#
0(
b11 K
1&
b100010 H
b101 M
10
#910000
00
#915000
b100010 "
b100010 9
b100010 P
0$
1#
1(
b110001 %
b110001 :
b110001 O
b110001 D
b1 F
b11 M
0&
10
#920000
b1 K
00
1,
#925000
bz "
bz 9
bz P
0)
1$
0#
0(
1&
b1 M
10
#930000
bz !
bz 8
00
04
0.
01
0,
#935000
0&
10
#940000
00
#945000
10
#950000
00
#955000
10
#960000
b1110111 !
b1110111 8
b10 K
00
b1110111 5
b1000000 -
b1000000 6
b1 /
b1 7
14
12
#965000
1)
b11 K
b1110111 H
b0 F
b1 G
0E
b1000000 %
b1000000 :
b1000000 O
b1000000 D
b10 M
10
#970000
00
#975000
b1110111 "
b1110111 9
b1110111 P
0$
1#
1(
b11 M
10
#980000
00
#985000
b1 K
1&
10
#990000
bz !
bz 8
b1 K
00
04
02
#995000
bz "
bz 9
bz P
0)
1$
0#
0(
1I
b1 M
1&
10
#1000000
00
#1005000
0&
1I
10
#1010000
00
#1015000
0I
10
#1020000
b10 K
00
12
#1025000
1)
b100 K
0L
b10 M
10
#1030000
00
#1035000
1'
1(
b100 M
10
#1040000
00
#1045000
b1110111 !
b1110111 8
b1110111 "
b1110111 9
b1110111 P
b1 K
1&
b1110111 T
10
#1050000
b1 K
00
02
#1055000
bz "
bz 9
bz P
0)
bz !
bz 8
0'
0(
1I
b1 M
1&
10
#1060000
00
#1065000
0&
1I
10
#1070000
00
#1075000
0I
10
