sources_1/new/spsram.v
`timescale 1ns / 1ps
module spsram #(parameter DATA_WIDTH = 8,parameter ADDRESS_WIDTH = 8
)(
input wire  clk,wre,oe,ce,rst,
input wire [ADDRESS_WIDTH-1:0]addr,
inout wire [DATA_WIDTH-1:0]data, // bidirectional data bus
output reg status
    );
    localparam DEPTH = 2**ADDRESS_WIDTH;

    reg [DATA_WIDTH-1:0] mem[0:DEPTH-1];
    reg [DATA_WIDTH-1:0] TEMPDATA;

    always @(posedge clk or negedge rst)
        begin

            if(!rst)
                begin
                status <= 1'b0;
                TEMPDATA <= 0;
                end

            else

                begin
                status <= 0;
                if(wre && ce)
                    begin
                        mem[addr] <= data;
                        status <= 1'b1;
                    end
                else if(oe && !wre && ce)
                    begin
                        TEMPDATA <= mem[addr];
                        status <= 1'b1;
                    end
            end
    end
    assign data = (!wre && ce && oe&& status)? TEMPDATA:{DATA_WIDTH{1'hz}};

endmodule

sources_1/new/controller.v
`timescale 1ns / 1ps

module controller #(parameter DATA_WIDTH = 8, parameter ADDRESS_WIDTH = 8)(
input wire req,rw,clk,rst,bmode,abort,ram_stat,data_valid,
input [3:0]burst_len,
inout wire [DATA_WIDTH-1:0]data_cn_ram,
input wire [ADDRESS_WIDTH-1:0]addr,
output wire [ADDRESS_WIDTH-1:0]sram_addr,
output reg wre,oe,ce,tri_o,
output reg done,error_flag,
output busy,
inout wire [DATA_WIDTH-1:0]data_cn_in_out
    );
    //internal registers
    reg [ADDRESS_WIDTH-1:0]addr_reg;
    reg [DATA_WIDTH-1:0] data_reg;
    reg [1:0]try;
    reg rw_reg,bmode_reg;
    reg [3:0]state,next_state;
    reg [3:0]burst_len_reg;
    reg [3:0]burst_count;
    //internal registers

    //local parameters
    localparam IDLE = 4'b0001;
    localparam PRE_IDLE = 4'b0000;
    localparam PRE = 4'b0010;
    localparam WRITE = 4'b0011;
    localparam READ = 4'b0100;
    localparam BE = 4'b0101;

    localparam MAXTRY = 2'b11;

    //local parameters

    //cont assignments
    assign data_cn_ram = tri_o == 0? data_reg : {DATA_WIDTH{1'hz}};
    assign busy = (state == IDLE || state == PRE_IDLE)? 1'b0:1'b1;
    assign sram_addr = addr_reg;
    assign data_cn_in_out = (state == READ && tri_o == 1)? data_cn_ram : {DATA_WIDTH{1'hz}};
    //cont assignments

    //state-register
    always @(posedge clk or negedge rst)
        begin
            if(!rst)
                begin
                    state <= PRE_IDLE;
                    try <= 2'b00;
                    addr_reg  <= 0;
                    data_reg  <= 0;
                    rw_reg    <= 0;
                    error_flag <=0;
                    done <=0;
                    burst_count <= 1'b0;
                    bmode_reg <= 0;
                    burst_len_reg <= 0;

                end
             else
             begin
                state <= next_state;
                done <= 0;

                    if(state == IDLE && req)
                        begin
                            addr_reg <= addr;
                            rw_reg <= rw;

                            bmode_reg <= bmode;
                            burst_len_reg <= burst_len;
                            burst_count <= 1'b0;
                            error_flag <=0;
                            if(rw)
                                data_reg <= data_cn_in_out;
                        end
                    else if(state == BE)
                    begin
                            if(rw_reg && bmode_reg && ram_stat && burst_count < burst_len_reg -1)
                            begin

                                burst_count <= burst_count +1'b1;
                                addr_reg <= addr_reg + 1'b1;
                            end
                            else if((~rw_reg && bmode_reg && ram_stat) && burst_count <burst_len_reg - 1)
                            begin
                                burst_count <= burst_count +1'b1;
                                addr_reg <= addr_reg + 1'b1;
                            end


                    end


                    else if(state == WRITE)
                            begin
                                if(ram_stat && bmode_reg)
                                    begin
                                            if(burst_count < burst_len_reg -1)
                                                begin
                                                    data_reg <= data_cn_in_out;

                                                end
                                    end
                         end


                end
        end
    //state-register

    //next-state-logic
        always @(*)

        begin
        next_state = state;
        if(abort)
            next_state = IDLE;
        else
            begin
            case(state)

                PRE_IDLE : next_state = IDLE;

                IDLE: begin
                            if(req)
                            next_state = PRE;
                            else
                            next_state = IDLE;
                        end

                PRE: begin
                            if(rw_reg)
                            next_state = WRITE;
                            else
                            next_state = READ;
                     end
                WRITE: begin
                            if(ram_stat && bmode_reg)
                                begin

                                            if(burst_count < burst_len_reg -1)
                                                next_state = BE;
                                            else
                                                next_state = IDLE;

                                end
                            else if(ram_stat && ~bmode_reg)
                                        next_state = IDLE;
                        end
                READ: begin
                            if(ram_stat && bmode_reg)
                                begin
                                            if(burst_count < burst_len_reg -1)
                                                next_state = BE;
                                            else
                                                next_state = IDLE;


                                end
                            else if(ram_stat && ~bmode_reg)
                                        next_state = IDLE;
                        end
                BE:
                    begin
                        if(bmode_reg && rw_reg)
                            next_state = WRITE;
                        else if(bmode_reg && ~rw_reg)
                            next_state = READ;
                        else
                            next_state = IDLE;
                    end
            endcase
            end
        end
    //next-state-logic

    //output logic
        always @(*)
                begin
                    case(state)
                        PRE_IDLE:
                            begin
                                ce = 1'b0;
                                oe = 1'b0;
                                wre = 1'b0;
                                tri_o = 1'b1;
                            end
                        IDLE:
                            begin
                                ce = 1'b0;
                                oe = 1'b0;
                                wre = 1'b0;
                                tri_o = 1'b1;
                            end
                        PRE:
                            begin
                                ce = 1'b0;
                                oe = 1'b0;
                                wre = 1'b0;
                                tri_o = 1'b1;
                            end
                        WRITE:
                            begin
                                ce = 1'b1;
                                oe = 1'b0;
                                wre = 1'b1;
                                tri_o = 1'b0;
                            end
                         READ:
                            begin
                                ce = 1'b1;
                                oe = 1'b1;
                                wre = 1'b0;
                                tri_o = 1'b1;
                            end
                          BE:
                            begin
                                ce = 1'b0;
                                oe = 1'b0;
                                wre = 1'b0;
                                tri_o = 1'b1;
                            end
                    endcase
                end
    //output logic
endmodule

sim_1/new/controller_tb.v
`timescale 1ns / 1ps
module controller_tb(

    );
        parameter DATA_WIDTH = 8;
        parameter ADDRESS_WIDTH = 8;
        reg req,rw,clk,rst,bmode,abort;
        reg [3:0]burst_len;
        wire [DATA_WIDTH-1:0]data_cn_ram;
        reg [ADDRESS_WIDTH-1:0]addr;
        wire wre,oe,ce,tri_o;
        wire ram_stat;
        wire busy;
        wire [ADDRESS_WIDTH-1:0]sram_addr;
        wire [DATA_WIDTH-1:0]data_cn_in_out;
        reg [DATA_WIDTH-1:0]test_data;
        reg data_valid;
        controller uut(
            .clk(clk),
            .rst(rst),
            .req(req),
            .rw(rw),
            .bmode(bmode),
            .abort(abort),
            .ram_stat(ram_stat),
            .burst_len(burst_len),
            .data_cn_ram(data_cn_ram),
            .addr(addr),
            .wre(wre),
            .oe(oe),
            .ce(ce),
            .tri_o(tri_o),
            .busy(busy),
            .data_cn_in_out(data_cn_in_out),
            .sram_addr(sram_addr),
            .data_valid(data_valid)

        );
        spsram uut1(
        .oe(oe),
        .wre(wre),
        .ce(ce),
        .addr(sram_addr),
        .data(data_cn_ram),
        .status(ram_stat),
        .clk(clk),
        .rst(rst)
        );

        assign data_cn_in_out = (rw) ? test_data : {DATA_WIDTH{1'bz}};
        always #5 clk = ~clk;

        initial begin
            $dumpfile("wave.vcd");
            $dumpvars(0,controller_tb);
    clk = 0;
    rst = 1'b0;
    addr = 0;
    req = 0;
    rw = 0;
    bmode = 0;
    test_data = 0;
    abort = 0;
    burst_len = 4'b0000;
    data_valid = 0;
    // Reset
    #10;
    rst = 1'b1;
    #20;
        addr = 8'h01;
        req = 1'b1;
        bmode = 1'b1;
        rw = 1'b1;
        burst_len = 4'd3;

        test_data = 8'h02;
        data_valid = 1'b1;

        #30;
        req = 1'b0;

        test_data = 8'h03;
        data_valid = 1'b1;

        #30;
        test_data = 8'h07;
        data_valid = 1'b1;

        #30;
        data_valid = 1'b0;
        bmode = 1'b0;
        rw = 1'b0;

        #30;
        req = 1'b1;
        bmode = 1'b1;
        addr = 8'h01;
        #90;
        req = 1'b0;
        #30;
        req = 1'b1;
        rw = 1'b1;
        test_data = 8'h05;
        bmode = 1'b0;
        addr = 8'h04;
        #30;
        req = 1'b0;
        #30
        req = 1'b1;
        rw = 1'b0;

        addr = 8'h04;
        #30;
        req = 1'b0;
        #30;


    $finish;
end
endmodule

wave.vcd
$date
	Tue Sep 15 12:31:15 2026
$end
$version
	Icarus Verilog
$end
$timescale
	1ps
$end
$scope module controller_tb $end
$var wire 8 ! data_cn_in_out [7:0] $end
$var wire 8 " data_cn_ram [7:0] $end
$var wire 1 # wre $end
$var wire 1 $ tri_o $end
$var wire 8 % sram_addr [7:0] $end
$var wire 1 & ram_stat $end
$var wire 1 ' oe $end
$var wire 1 ( ce $end
$var wire 1 ) busy $end
$var parameter 32 * ADDRESS_WIDTH $end
$var parameter 32 + DATA_WIDTH $end
$var reg 1 , abort $end
$var reg 8 - addr [7:0] $end
$var reg 1 . bmode $end
$var reg 4 / burst_len [3:0] $end
$var reg 1 0 clk $end
$var reg 1 1 data_valid $end
$var reg 1 2 req $end
$var reg 1 3 rst $end
$var reg 1 4 rw $end
$var reg 8 5 test_data [7:0] $end
$scope module uut $end
$var wire 1 , abort $end
$var wire 8 6 addr [7:0] $end
$var wire 1 . bmode $end
$var wire 4 7 burst_len [3:0] $end
$var wire 1 0 clk $end
$var wire 8 8 data_cn_in_out [7:0] $end
$var wire 8 9 data_cn_ram [7:0] $end
$var wire 1 1 data_valid $end
$var wire 1 2 req $end
$var wire 1 3 rst $end
$var wire 1 4 rw $end
$var wire 8 : sram_addr [7:0] $end
$var wire 1 & ram_stat $end
$var wire 1 ) busy $end
$var parameter 32 ; ADDRESS_WIDTH $end
$var parameter 4 < BE $end
$var parameter 32 = DATA_WIDTH $end
$var parameter 4 > IDLE $end
$var parameter 2 ? MAXTRY $end
$var parameter 4 @ PRE $end
$var parameter 4 A PRE_IDLE $end
$var parameter 4 B READ $end
$var parameter 4 C WRITE $end
$var reg 8 D addr_reg [7:0] $end
$var reg 1 E bmode_reg $end
$var reg 4 F burst_count [3:0] $end
$var reg 4 G burst_len_reg [3:0] $end
$var reg 1 ( ce $end
$var reg 8 H data_reg [7:0] $end
$var reg 1 I done $end
$var reg 1 J error_flag $end
$var reg 4 K next_state [3:0] $end
$var reg 1 ' oe $end
$var reg 1 L rw_reg $end
$var reg 4 M state [3:0] $end
$var reg 1 $ tri_o $end
$var reg 2 N try [1:0] $end
$var reg 1 # wre $end
$upscope $end
$scope module uut1 $end
$var wire 8 O addr [7:0] $end
$var wire 1 ( ce $end
$var wire 1 0 clk $end
$var wire 8 P data [7:0] $end
$var wire 1 ' oe $end
$var wire 1 3 rst $end
$var wire 1 # wre $end
$var parameter 32 Q ADDRESS_WIDTH $end
$var parameter 32 R DATA_WIDTH $end
$var parameter 32 S DEPTH $end
$var reg 8 T TEMPDATA [7:0] $end
$var reg 1 & status $end
$upscope $end
$upscope $end
$enddefinitions $end
$comment Show the parameter values. $end
$dumpall
b100000000 S
b1000 R
b1000 Q
b11 C
b100 B
b0 A
b10 @
b11 ?
b1 >
b1000 =
b101 <
b1000 ;
b1000 +
b1000 *
$end
#0
$dumpvars
b0 T
bz P
b0 O
b0 N
b0 M
0L
b1 K
0J
0I
b0 H
b0 G
b0 F
0E
b0 D
b0 :
bz 9
bz 8
b0 7
b0 6
b0 5
04
03
02
01
00
b0 /
0.
b0 -
0,
0)
0(
0'
0&
b0 %
1$
0#
bz "
bz !
$end
#5000
10
#10000
00
13
#15000
b1 M
10
#20000
00
#25000
10
#30000
b10 !
b10 8
b10 K
00
11
b10 5
b11 /
b11 7
14
1.
12
b1 -
b1 6
#35000
1)
b11 K
b10 H
b11 G
1E
1L
b1 %
b1 :
b1 O
b1 D
b10 M
10
#40000
00
#45000
b10 "
b10 9
b10 P
0$
1#
1(
b11 M
10
#50000
00
#55000
b101 K
1&
10
#60000
b11 !
b11 8
b101 K
00
b11 5
02
#65000
bz "
bz 9
bz P
1$
0#
0(
b11 K
1&
b11 H
b101 M
10
#70000
00
#75000
b11 "
b11 9
b11 P
0$
1#
1(
b10 %
b10 :
b10 O
b10 D
b1 F
b11 M
0&
10
#80000
00
#85000
b101 K
1&
10
#90000
b111 !
b111 8
00
b111 5
#95000
bz "
bz 9
bz P
1$
0#
0(
b11 K
b111 H
b101 M
1&
10
#100000
00
#105000
b111 "
b111 9
b111 P
0$
1#
1(
0&
b11 %
b11 :
b11 O
b11 D
b10 F
b11 M
10
#110000
00
#115000
b1 K
1&
10
#120000
bz !
bz 8
00
04
0.
01
#125000
bz "
bz 9
bz P
0)
1$
0#
0(
1&
b1 M
10
#130000
00
#135000
0&
10
#140000
00
#145000
10
#150000
b10 K
00
1.
12
#155000
1)
b100 K
b0 F
0L
b1 %
b1 :
b1 O
b1 D
b10 M
10
#160000
00
#165000
1'
1(
b100 M
10
#170000
00
#175000
b10 !
b10 8
b10 "
b10 9
b10 P
b101 K
1&
b10 T
10
#180000
00
#185000
bz "
bz 9
bz P
bz !
bz 8
0'
0(
b100 K
1&
b101 M
10
#190000
00
#195000
1'
1(
b10 %
b10 :
b10 O
b10 D
b1 F
b100 M
0&
10
#200000
00
#205000
b11 !
b11 8
b11 "
b11 9
b11 P
b101 K
1&
b11 T
10
#210000
00
#215000
bz "
bz 9
bz P
bz !
bz 8
0'
0(
b100 K
b101 M
1&
10
#220000
00
#225000
1'
1(
0&
b11 %
b11 :
b11 O
b11 D
b10 F
b100 M
10
#230000
00
#235000
b111 !
b111 8
b111 "
b111 9
b111 P
b1 K
1&
b111 T
10
#240000
b1 K
00
02
#245000
bz "
bz 9
bz P
0)
bz !
bz 8
0'
0(
1&
b1 M
10
#250000
00
#255000
0&
10
#260000
00
#265000
10
#270000
b101 !
b101 8
b10 K
00
b100 -
b100 6
0.
b101 5
14
12
#275000
1)
b11 K
b101 H
b0 F
0E
1L
b100 %
b100 :
b100 O
b100 D
b10 M
10
#280000
00
#285000
b101 "
b101 9
b101 P
0$
1#
1(
b11 M
10
#290000
00
#295000
b1 K
1&
10
#300000
b1 K
00
02
#305000
bz "
bz 9
bz P
0)
1$
0#
0(
1&
b1 M
10
#310000
00
#315000
0&
10
#320000
00
#325000
10
#330000
bz !
bz 8
b10 K
00
04
12
#335000
1)
b100 K
0L
b10 M
10
#340000
00
#345000
1'
1(
b100 M
10
#350000
00
#355000
b101 !
b101 8
b101 "
b101 9
b101 P
b1 K
1&
b101 T
10
#360000
b1 K
00
02
#365000
bz "
bz 9
bz P
0)
bz !
bz 8
0'
0(
1&
b1 M
10
#370000
00
#375000
0&
10
